{
    "album_name": "2.13.18 | Port City Music Hall | Portland, ME",
    "album_link": "https://papadosio.bandcamp.com/album/21318-port-city-music-hall-portland-me",
    "date_modified": "20 Feb 2018 18:53:33 GMT",
    "album_artwork": "https://f4.bcbits.com/img/a3050086251_10.jpg",
    "date_published": "20 Feb 2018 18:53:33 GMT",
    "album_duration": "P01H40M22S",
    "track_list": [
        {
            "track_name": "Euclidean Lights",
            "track_link": "https://papadosio.bandcamp.com/track/euclidean-lights-34",
            "track_duration": "P00H10M05S"
        },
        {
            "track_name": "We Choose",
            "track_link": "https://papadosio.bandcamp.com/track/we-choose-35",
            "track_duration": "P00H06M25S"
        },
        {
            "track_name": "New Love",
            "track_link": "https://papadosio.bandcamp.com/track/new-love-117",
            "track_duration": "P00H16M42S"
        },
        {
            "track_name": "Advocate of Change",
            "track_link": "https://papadosio.bandcamp.com/track/advocate-of-change-67",
            "track_duration": "P00H07M57S"
        },
        {
            "track_name": "Drift",
            "track_link": "https://papadosio.bandcamp.com/track/drift-31",
            "track_duration": "P00H05M59S"
        },
        {
            "track_name": "Cue",
            "track_link": "https://papadosio.bandcamp.com/track/cue-103",
            "track_duration": "P00H13M39S"
        },
        {
            "track_name": "Geoglyph",
            "track_link": "https://papadosio.bandcamp.com/track/geoglyph-54",
            "track_duration": "P00H09M51S"
        },
        {
            "track_name": "Madre de Dios",
            "track_link": "https://papadosio.bandcamp.com/track/madre-de-dios-31",
            "track_duration": "P00H04M47S"
        },
        {
            "track_name": "Night Colors",
            "track_link": "https://papadosio.bandcamp.com/track/night-colors-64",
            "track_duration": "P00H12M57S"
        },
        {
            "track_name": "Threes",
            "track_link": "https://papadosio.bandcamp.com/track/threes-40",
            "track_duration": "P00H12M00S"
        }
    ]
}