{
    "album_name": "2013-04-24 - Terminal West - Atlanta, GA",
    "album_link": "https://papadosio.bandcamp.com/album/2013-04-24-terminal-west-atlanta-ga",
    "date_modified": "23 Apr 2015 17:50:11 GMT",
    "album_artwork": "https://f4.bcbits.com/img/a0387393175_10.jpg",
    "date_published": "22 May 2013 00:00:00 GMT",
    "album_duration": "P02H04M57S",
    "track_list": [
        {
            "track_name": "Utopiate",
            "track_link": "https://papadosio.bandcamp.com/track/utopiate-2",
            "track_duration": "P00H12M14S"
        },
        {
            "track_name": "How Not to Float",
            "track_link": "https://papadosio.bandcamp.com/track/how-not-to-float-2",
            "track_duration": "P00H07M59S"
        },
        {
            "track_name": "Magreenery",
            "track_link": "https://papadosio.bandcamp.com/track/magreenery-2",
            "track_duration": "P00H22M12S"
        },
        {
            "track_name": "Right Now",
            "track_link": "https://papadosio.bandcamp.com/track/right-now-3",
            "track_duration": "P00H08M17S"
        },
        {
            "track_name": "The Bionic Man Meets His Past",
            "track_link": "https://papadosio.bandcamp.com/track/the-bionic-man-meets-his-past-2",
            "track_duration": "P00H06M33S"
        },
        {
            "track_name": "Unparalyzer",
            "track_link": "https://papadosio.bandcamp.com/track/unparalyzer-4",
            "track_duration": "P00H17M46S"
        },
        {
            "track_name": "Cue",
            "track_link": "https://papadosio.bandcamp.com/track/cue-3",
            "track_duration": "P00H13M09S"
        },
        {
            "track_name": "If It Wasn't For You",
            "track_link": "https://papadosio.bandcamp.com/track/if-it-wasnt-for-you-4",
            "track_duration": "P00H07M54S"
        },
        {
            "track_name": "Polygons",
            "track_link": "https://papadosio.bandcamp.com/track/polygons-3",
            "track_duration": "P00H14M38S"
        },
        {
            "track_name": "Snorkle",
            "track_link": "https://papadosio.bandcamp.com/track/snorkle-3",
            "track_duration": "P00H14M15S"
        }
    ]
}