{
    "album_name": "Camp Bisco | 7.18.15 | Montage Mountain, PA",
    "album_link": "https://papadosio.bandcamp.com/album/camp-bisco-71815-montage-mountain-pa",
    "date_modified": "21 Aug 2015 04:06:27 GMT",
    "album_artwork": "https://f4.bcbits.com/img/a1210839485_10.jpg",
    "date_published": "21 Aug 2015 04:06:27 GMT",
    "album_duration": "P00H49M45S",
    "track_list": [
        {
            "track_name": "Paradigm Shift",
            "track_link": "https://papadosio.bandcamp.com/track/paradigm-shift-38",
            "track_duration": "P00H09M24S"
        },
        {
            "track_name": "Smile and Nod",
            "track_link": "https://papadosio.bandcamp.com/track/smile-and-nod-38",
            "track_duration": "P00H09M20S"
        },
        {
            "track_name": "Psypoly",
            "track_link": "https://papadosio.bandcamp.com/track/psypoly",
            "track_duration": "P00H04M11S"
        },
        {
            "track_name": "Fuse",
            "track_link": "https://papadosio.bandcamp.com/track/fuse-36",
            "track_duration": "P00H08M45S"
        },
        {
            "track_name": "Improbability Blotter",
            "track_link": "https://papadosio.bandcamp.com/track/improbability-blotter-37",
            "track_duration": "P00H12M52S"
        },
        {
            "track_name": "Paradigm Shift",
            "track_link": "https://papadosio.bandcamp.com/track/paradigm-shift-39",
            "track_duration": "P00H05M13S"
        }
    ]
}