{
    "album_name": "Live at Higher Ground - Imaginal Cells Tour",
    "album_link": "https://papadosio.bandcamp.com/album/live-at-higher-ground-imaginal-cells-tour",
    "date_modified": "28 Oct 2014 00:01:58 GMT",
    "album_artwork": "https://f4.bcbits.com/img/a1163136993_10.jpg",
    "date_published": "26 Oct 2014 00:00:00 GMT",
    "album_duration": "P02H08M00S",
    "track_list": [
        {
            "track_name": "The Lack of Everything",
            "track_link": "https://papadosio.bandcamp.com/track/the-lack-of-everything-6",
            "track_duration": "P00H07M29S"
        },
        {
            "track_name": "Find Your Cloud",
            "track_link": "https://papadosio.bandcamp.com/track/find-your-cloud-43",
            "track_duration": "P00H18M20S"
        },
        {
            "track_name": "Hippie Babysitter",
            "track_link": "https://papadosio.bandcamp.com/track/hippie-babysitter-17",
            "track_duration": "P00H13M42S"
        },
        {
            "track_name": "Cue",
            "track_link": "https://papadosio.bandcamp.com/track/cue-35",
            "track_duration": "P00H11M48S"
        },
        {
            "track_name": "If It Wasn't For you",
            "track_link": "https://papadosio.bandcamp.com/track/if-it-wasnt-for-you-29",
            "track_duration": "P00H07M45S"
        },
        {
            "track_name": "We Choose",
            "track_link": "https://papadosio.bandcamp.com/track/we-choose-17",
            "track_duration": "P00H06M36S"
        },
        {
            "track_name": "Oracle Theme",
            "track_link": "https://papadosio.bandcamp.com/track/oracle-theme-16",
            "track_duration": "P00H09M34S"
        },
        {
            "track_name": "Utopiate",
            "track_link": "https://papadosio.bandcamp.com/track/utopiate-25",
            "track_duration": "P00H12M20S"
        },
        {
            "track_name": "In the Meantime*",
            "track_link": "https://papadosio.bandcamp.com/track/in-the-meantime",
            "track_duration": "P00H04M38S"
        },
        {
            "track_name": "You and Yourself",
            "track_link": "https://papadosio.bandcamp.com/track/you-and-yourself-17",
            "track_duration": "P00H13M28S"
        },
        {
            "track_name": "We Are Water>",
            "track_link": "https://papadosio.bandcamp.com/track/we-are-water-47",
            "track_duration": "P00H07M28S"
        },
        {
            "track_name": "The Plug",
            "track_link": "https://papadosio.bandcamp.com/track/the-plug-20",
            "track_duration": "P00H14M52S"
        }
    ]
}