{
    "album_name": "Papadosio and Friends Improv Set | Secret Dreams Festival | 9.19.22",
    "album_link": "https://papadosio.bandcamp.com/album/papadosio-and-friends-improv-set-secret-dreams-festival-91922",
    "date_modified": "07 Sep 2022 17:35:55 GMT",
    "album_artwork": "https://f4.bcbits.com/img/a4261675736_10.jpg",
    "date_published": "07 Sep 2022 17:35:56 GMT",
    "album_duration": "P01H08M46S",
    "track_list": [
        {
            "track_name": "Speech To T-Rext",
            "track_link": "https://papadosio.bandcamp.com/track/speech-to-t-rext",
            "track_duration": "P00H14M10S"
        },
        {
            "track_name": "Flying ft. Pablo Falbru",
            "track_link": "https://papadosio.bandcamp.com/track/flying-ft-pablo-falbru",
            "track_duration": "P00H10M47S"
        },
        {
            "track_name": "Into The Gortex Vortex ft. James Eddington",
            "track_link": "https://papadosio.bandcamp.com/track/into-the-gortex-vortex-ft-james-eddington",
            "track_duration": "P00H09M28S"
        },
        {
            "track_name": "Mai Gorl ft. Mike Martinez",
            "track_link": "https://papadosio.bandcamp.com/track/mai-gorl-ft-mike-martinez",
            "track_duration": "P00H08M11S"
        },
        {
            "track_name": "Jee Mynour ft. Nick Gerlach",
            "track_link": "https://papadosio.bandcamp.com/track/jee-mynour-ft-nick-gerlach",
            "track_duration": "P00H12M26S"
        },
        {
            "track_name": "Dirty Gantzin",
            "track_link": "https://papadosio.bandcamp.com/track/dirty-gantzin",
            "track_duration": "P00H13M44S"
        }
    ]
}