{
    "@id": "https://papadosio.bandcamp.com/album/6818-music-farm-charleston-sc",
    "name": "6.8.18 | Music Farm | Charleston, SC",
    "dateModified": "10 Jul 2018 22:35:51 GMT",
    "numTracks": 10,
    "track": {
        "numberOfItems": 10,
        "itemListElement": [
            {
                "position": 1,
                "item": {
                    "name": "Paradigm Shift",
                    "duration": "P00H06M56S",
                    "mainEntityOfPage": "https://papadosio.bandcamp.com/track/paradigm-shift-79"
                }
            },
            {
                "position": 2,
                "item": {
                    "name": "Cushion",
                    "duration": "P00H06M13S",
                    "mainEntityOfPage": "https://papadosio.bandcamp.com/track/cushion-60"
                }
            },
            {
                "position": 3,
                "item": {
                    "name": "Paradigm Reprise",
                    "duration": "P00H11M48S",
                    "mainEntityOfPage": "https://papadosio.bandcamp.com/track/paradigm-reprise-2"
                }
            },
            {
                "position": 4,
                "item": {
                    "name": "Garden",
                    "duration": "P00H09M35S",
                    "mainEntityOfPage": "https://papadosio.bandcamp.com/track/garden-88"
                }
            },
            {
                "position": 5,
                "item": {
                    "name": "Method of Control",
                    "duration": "P00H09M13S",
                    "mainEntityOfPage": "https://papadosio.bandcamp.com/track/method-of-control-87"
                }
            },
            {
                "position": 6,
                "item": {
                    "name": "Smile and Nod",
                    "duration": "P00H09M55S",
                    "mainEntityOfPage": "https://papadosio.bandcamp.com/track/smile-and-nod-68"
                }
            },
            {
                "position": 7,
                "item": {
                    "name": "The Bionic Man Meets His Past",
                    "duration": "P00H16M19S",
                    "mainEntityOfPage": "https://papadosio.bandcamp.com/track/the-bionic-man-meets-his-past-100"
                }
            },
            {
                "position": 8,
                "item": {
                    "name": "The Plug",
                    "duration": "P00H14M41S",
                    "mainEntityOfPage": "https://papadosio.bandcamp.com/track/the-plug-49"
                }
            },
            {
                "position": 9,
                "item": {
                    "name": "Holy Heck",
                    "duration": "P00H07M14S",
                    "mainEntityOfPage": "https://papadosio.bandcamp.com/track/holy-heck-40"
                }
            },
            {
                "position": 10,
                "item": {
                    "name": "Unparalyzer",
                    "duration": "P00H17M30S",
                    "mainEntityOfPage": "https://papadosio.bandcamp.com/track/unparalyzer-85"
                }
            }
        ],
        "duration": "P01H49M24S"
    },
    "image": "https://f4.bcbits.com/img/a2435341599_10.jpg",
    "datePublished": "10 Jul 2018 22:35:51 GMT",
    "description": "This album was recorded on June 8th in Charleston, SC! Summer Tour is in full effect! Thanks to The Music Farm for Having us out and thanks to Schema for opening the night up!"
}