{
    "@id": "https://papadosio.bandcamp.com/album/the-national-richmond-va-51824",
    "name": "The National | Richmond, VA | 5.18.24",
    "dateModified": "22 May 2024 19:06:05 GMT",
    "numTracks": 12,
    "track": {
        "numberOfItems": 12,
        "itemListElement": [
            {
                "position": 1,
                "item": {
                    "name": "Cutting Through The Drama",
                    "duration": "P00H09M50S",
                    "mainEntityOfPage": "https://papadosio.bandcamp.com/track/cutting-through-the-drama-2"
                }
            },
            {
                "position": 2,
                "item": {
                    "name": "Fly Agaric",
                    "duration": "P00H10M08S",
                    "mainEntityOfPage": "https://papadosio.bandcamp.com/track/fly-agaric-44"
                }
            },
            {
                "position": 3,
                "item": {
                    "name": "Reishi",
                    "duration": "P00H06M30S",
                    "mainEntityOfPage": "https://papadosio.bandcamp.com/track/reishi-17"
                }
            },
            {
                "position": 4,
                "item": {
                    "name": "Knowledge Or Wisdom",
                    "duration": "P00H09M22S",
                    "mainEntityOfPage": "https://papadosio.bandcamp.com/track/knowledge-or-wisdom-2"
                }
            },
            {
                "position": 5,
                "item": {
                    "name": "New Love",
                    "duration": "P00H09M38S",
                    "mainEntityOfPage": "https://papadosio.bandcamp.com/track/new-love-178"
                }
            },
            {
                "position": 6,
                "item": {
                    "name": "Find Your Cloud",
                    "duration": "P00H15M35S",
                    "mainEntityOfPage": "https://papadosio.bandcamp.com/track/find-your-cloud-196"
                }
            },
            {
                "position": 7,
                "item": {
                    "name": "Spinning",
                    "duration": "P00H04M07S",
                    "mainEntityOfPage": "https://papadosio.bandcamp.com/track/spinning-11"
                }
            },
            {
                "position": 8,
                "item": {
                    "name": "Paradigm Shift",
                    "duration": "P00H12M44S",
                    "mainEntityOfPage": "https://papadosio.bandcamp.com/track/paradigm-shift-134"
                }
            },
            {
                "position": 9,
                "item": {
                    "name": "Mr. Turtle's Cloud Kingdom",
                    "duration": "P00H05M30S",
                    "mainEntityOfPage": "https://papadosio.bandcamp.com/track/mr-turtles-cloud-kingdom-77"
                }
            },
            {
                "position": 10,
                "item": {
                    "name": "Everyone Is Cool",
                    "duration": "P00H09M59S",
                    "mainEntityOfPage": "https://papadosio.bandcamp.com/track/everyone-is-cool-23"
                }
            },
            {
                "position": 11,
                "item": {
                    "name": "Glimpse Of Light",
                    "duration": "P00H06M00S",
                    "mainEntityOfPage": "https://papadosio.bandcamp.com/track/glimpse-of-light-64"
                }
            },
            {
                "position": 12,
                "item": {
                    "name": "We Are Water",
                    "duration": "P00H16M55S",
                    "mainEntityOfPage": "https://papadosio.bandcamp.com/track/we-are-water-183"
                }
            }
        ],
        "duration": "P01H56M18S"
    },
    "image": "https://f4.bcbits.com/img/a3344606897_10.jpg",
    "datePublished": "22 May 2024 19:06:05 GMT",
    "description": "So great to be back in Richmond at The National and for our EP release to boot! Thanks everyone for coming out and boogyin'!"
}